FOXIS64/__init__.py
FOXIS64/main.py
FOXIS64-0.0.1.dist-info/License
FOXIS64-0.0.1.dist-info/METADATA
FOXIS64-0.0.1.dist-info/WHEEL
FOXIS64-0.0.1.dist-info/top_level.txt
FOXIS64-0.0.1.dist-info/RECORD
