Metadata-Version: 2.1
Name: FOXIS64
Version: 0.0.1
Summary: For users
Home-page: UNKNOWN
Author: Ann
Author-email: Anyasutiko6403938@gmail.com
License: UNKNOWN
Platform: UNKNOWN
Classifier: Programming Language :: Python :: 3.6
Classifier: License :: OSI Approved :: MIT License
Classifier: Operating System :: OS Independent
Requires-Python: >=3.8
License-File: License
